{
    "job_position_name": "Medical Assistant – Outpatient Clinic",
    "educational_requirements": "Associate or Bachelor’s degree in Healthcare Management, Nursing, or related field.",
    "experience_requirement": "2+ years of experience as a Medical Assistant, preferably in hospital or rapid care clinic settings.",
    "age_requirement": "",
    "responsibilities": [
        "Prepare examination rooms and set up medical instruments/equipment per clinic protocols.",
        "Record patient medical histories, vital signs, and concerns using EHR systems.",
        "Assist physicians during examinations, procedures, and minor treatments.",
        "Administer injections and perform EKGs under supervision.",
        "Ensure HIPAA compliance and patient confidentiality.",
        "Support front-desk operations and patient follow-up.",
        "Provide empathetic assistance with daily care and mobility support."
    ],
    "skills_required": [
        "Patient Assessment & Care",
        "Clinical Documentation (EHR)",
        "Administering Injections & EKGs",
        "HIPAA Compliance",
        "Team Collaboration",
        "Bilingual English/Spanish"
    ]
}